{
  "landing":"/partials/landing.html",
  "footer":"/partials/footer.html",
  "header":"/partials/header.html",
  "signup":{
    "user1":"/partials/signup/user.html",
    "user2":"/partials/signup/user-details.html",
    "user3":"/partials/signup/user-congrats.html",
    "company1":"/partials/signup/company.html",
    "company2":"/partials/signup/company-details.html",
    "company3":"/partials/signup/company-congrats.html"
  },
  "edit":{
    "user":"/partials/edit/user.html",
    "company":"/partials/edit/company.html"
  },
  "createPost":"/partials/create-post.html",
  "companyPage":"/partials/companyPage.html",
  "subscription": {
    "banner": "/partials/subscription/banner.html",
    "list": "/partials/subscription/list.html"
  },
  "myVacancy": {
    "banner": "/partials/my-vacancy/banner.html",
    "list": "/partials/my-vacancy/list.html"
  }
}